{
    "header": {
        "target": "a",
        "formatVersion": 5,
        "hidef": false,
        "compressed": true
    },
    "readers": [
        {
            "type": "Microsoft.Xna.Framework.Content.DictionaryReader`2[[System.String, mscorlib, Version=4.0.0.0, Culture=neutral, PublicKeyToken=b77a5c561934e089],[System.String, mscorlib, Version=4.0.0.0, Culture=neutral, PublicKeyToken=b77a5c561934e089]]",
            "version": 0
        },
        {
            "type": "Microsoft.Xna.Framework.Content.StringReader",
            "version": 0
        }
    ],
    "content": {
        "Introduction": "ÊħÊƤ! ĉ¹ҚÍ Gus ƱÍÒƚ¾àʛ¹àª¿ á̅Çʁàʛ¹ à˨Ò¢Í§̃Ò¹ÍÒËÒÃ Stardrop#$e#àˢÒÁÒƊ ˶ÒȤ³˵Í§ËÒà¤ҳÍ§ҤÁ ĉ¹Ʊ¡Òá¿̃Í¹æ áÅÐàƪÂΓàʢ¹æ ˴ÇÂ¹Ð$h",
        "willyCrabs": "àˤ¡ɫ¾Ç¡׉ ÍÒ¨¨Ðàʛ¹àˤ¡чƤчɊ´ чĉ¹à¤ÂŇÒÁÒàÅÂ˕Ð...",
        "Mon": "ãʺ, ĉ¹ړàҳÍ§ÃÒÇàÂÍÐáÂÐ àбÂÇāºڌ¤¹á¶Ç׉#$e#ġ¹ÍÒ¨¨Ðàʛ¹ˢÍƤÍ˒Ò§Ëѹ§ ¢Í§¡ÒÃàʛ¹ ºÒΓà·¹à´ÍΓʁä˴¹Ð$h#$e#á˅ºÒ§Ƨĉ¹ʁä˴Ƃ¹ ġ¹ÁÒ¡àš¹ä»àËȑÍ¹ā¹...",
        "pamHouseUpgrade": "à̎, ĉ¹ä˴ʲÒÇÁÒ˗Òà¸Íä»ʺÇÂÍÐäÃ Pam ÁÒ˺Ò§ à¸ÍщʺÒ§ƱթÒã¨Ƥ§ÒÁÁÒ¡æ àÅÂ!$h#$e#á˅ˉÒàÈ̃Ò, ĉ¹äˑŤ´˗Òġ¹ ¨ÐŇÒã̋à¸Íàƅ¡ 'ҤÁ' ¹Ð...",
        "pamHouseUpgradeAnonymous": "ĉ¹àʫ¹ Pam ʱÍ¹Ë˹Ò׉... à¸Í֢Á¡̇Ò§»Ò¡á·º¨Ðǖ§ɻàÅÂ!  à¸ÍºÍ¡˗ÒƱºÒ§¤¹ʸÒÂʴÒ˺Ò¹ Ëĥ§ãËˑã̋à¸Í!#$e#ã¤ÃʁµÒÁчŇÒáººԹ¹, ¾Ç¡à¢Ò¤ÇÃä˴ģºЪ§ƤæµÍºá·¹!$h",
        "Saloon": "ÊħÊƤµÍ¹àʢ¹ ¨ÐģºÍÐäÃƤ˕Ð?",
        "Saloon4": "ÊħÊƤµÍ¹àʢ¹ Ť´«Ð˗ÒàËȑÍ¹ ÍԒ˺Ò¹á̅Çā¹",
        "SeedShop_Entry": "ÊħÊƤ Pierre!/àÍÒ˕Ð ĉ¹˵Í§¡ÒÃÍÐäÃ˹ÒÒ.../ÍÒ ä̍ι¹ɤƤĈ§!/¨ÐŇÒ«ÍÊžàÈÉ ¢Í§ĉ¹Ǵ¹׉˕Ð!/Pierre! ƱÍÐäÃÊ´æ ˺Ò§?/Pierre! ¹ÒÂƱÍÐäÃã̋ĉ¹˕Ð?",
        "Saloon8": "ä§ ÊħÊƤ @ Ƥã¨чä˴à¨Í¹Ð! чщƂ¹Ƥ˵Í¹ģº à¸ÍàÊÁÍ",
        "Saloon_Tue": "ÊħÊƤ! Ğ¡ˌÍ¹ áÅÐʁ ¢Íã̋Êȹ¡¹Ð",
        "Saloon_Thu": "à̎ ɤàËȑÍ¹à¸ÍˉÒ¨ÐҤÁ ÍÐäÃĪ¡ËˉÍÂ¹Ð",
        "Saloon_Fri": "Ǵ¹׉ȸÃš¨ä»ä˴ÊÇÂÁÒ¡ ˉÒƂ¹Ƥ¨ƃ§æ",
        "Tue": "ĉ¹ŇÒÍÒËÒÃ áµ¡˅Ò§ā¹ȷ¡ÍÒŷµΒ  ÅÍ§ÁÒàʊ¤ɤ ʁá̅Çā¹¹Ð!#$e#Ȥ³ÍÒ¨¨Ðà¨Í ÍÒËÒÃ чɦ¡»Ò¡ʁä˴$h#$e#˶Òá˾ÍÐäÃ ʁºÍ¡ĉ¹˴ÇÂ˕Ð$s#$e#âÍà¤Ã  á̅Çà¨Íā¹",
        "Wed": "Emily ŇÒ§Ò¹чщ ÁÒä˴Ī¡Ğ¡á̅Ç˕Ð ĉ¹¤§äˑړ¨ÐŇÒĢ§ä§ ˶ÒäˑƱà¸Í!#$e#ĉ¹¤§à¡ƵÂ´ ч¨Ð˵Í§̅Ò§¾Ç¡Ë́Í àË˕ÒԹ¹Է§ËÁ´ ˴ÇÂĕÇàÍ§$s",
        "Thu": "Pam áÅÐ Clint ÁÒчºÒΓ á·º¨Ðȷ¡Ǵ¹#$e#¼Á¤§à̘§áˉ æ ˶ÒÊÍ§¤¹Թ¹äˑÁÒ$h#$e#á̅ÇÍ˒Òä»ä˕ ¾Ç¡à¢Ò˕Ð!",
        "Thu6": "Clint ÁÒчºÒΓàǱÍºȷ¡Ǵ¹ áÅÐι§ч»ÃÐĸÒ ḁ̂ÐàŴÁµÅÍ´#$e#ºÒ§¤Ճ§ʁàʫ¹à¢Ò àËȕÍºÁÍ§ Emily ˴ÇÂÊÒÂµÒчɤ »ÃÐËˑÒž¡Å țÁ...#$e#ºÒ§Ƨι¹ ÍÒ¨¨Ðàʛ¹ÊÒàËȵ чà¢ÒÁÒˊÍÂʁä˴ â̍щáËÅÐ áË˕§ŇÒàŧ¹Ԫ¹ƤàÅÂ˕Ð",
        "Thu8": "Pam ÁÒчºÒΓàǱÍº ¨Ðȷ¡Ǵ¹àÅÂ áÅÐҤÁàƪÂΓ ä»àÂÍÐÁÒ¡#$e#àÍÒà¶ÍÐ ĉ¹ʁäˑ¤ÇÃä» ĕ´Ɗ¹ÍÐäÃ āºɵ¡ˤÒĉ¹щ¹Ò",
        "Fri": "˗Òä§ @ ÊħÊƤ ˶Òà¸ÍÍÂÒ¡¨ÐҤÁ ŇÒäÁäˑáÇÐÁÒ чºÒΓĪ¡ËˉÍÂ˕Ð?",
        "Fri4": "ĉ¹äˑʴÍÂҤÁ àˇÒäË˓ËÃÍ¡ чŇÒÍԒʁàҮÍ »Ò¡˷Í§ËˉÐ#$e#ǖ§á́¨ÐÊȹ¡ ä»āº¡ÒÃ ŪÁÃÊªÒŵ¢Í§ Stardew Valley vintage àʛ¹ºÒ§¤Ճ§ʁà¶ÍÐ",
        "Sat": "Ȥ³àʱ§ŇÒ¤ģÇáʴäË¹ @?#$e#˶ÒȤ³Ʊ¤ģÇ āºɺµÃÍÒËÒÃĪ¡ËˉÍÂ Ȥ³¨ÐŇÒÍÒËÒÃчƱ »ÃÐâÂªΉä˴àÅÂ#$e#ÍÒËÒÃŇÒàÍ§ ʁàʛ¹¢Í§¢ħ­ чƤäˑ˹ÍÂ àʺ¹ā¹",
        "Sun": "ȸÃš¨ʴÍ¹ˢÒ§ ρ¹¤§á̅Ç ¢ÍºȤ³àË˕Òɵ¡ˤÒ »ÃÐĸÒԷ§ËÅÒÂ"
    }
}