{

"Mon": "้เจ้าเคยได้ยืนเรื่อง ปรากฏการณ์มิราจ มั้ยล่ะ? บางครั้งน่ะนะ ถ้ามีความร้อนเพียงพอ อากาศจะสั่นไหววิบวับ แล้วมันจะเหมือนกับว่า เจ้าได้เข้าไปยังต่างโลก$0",
"Tue": "*หาว* ที่นี่ซ้ำซากจำเจสุดๆ ข้าดีใจจริงๆ ที่เจ้าแวะมาหา$0",
"Wed": "ข้าได้ยินคน พูดถึงเจ้าบ่อยอยู่นะ @ เจ้าคงที่จะเป็นที่รู้จัก ในกิลด์ละสิ หื้ม?$1",
"Thu": "ข้ารอคอย อย่างใจจดใจจ่อเลย ที่จะได้กลับไปที่ลานนั่น การเฝ้ายามก็จำเป็นอยู่หรอก แต่ตอนนี้ข้าอยากไปบู้น่ะสิ$1",
"Sat": "มีอะไรให้ข้าช่วยมั้ยล่ะ @?$0#$e#ที่จริง ข้าก็อยากจะหาอะไร ให้เจ้าดื่มกิน ตอนที่อยู่นี่ล่ะนะ แต่เสบียงของเรามีจำกัดอ่ะ$2",
"Sun": "การเป็นนักผจญภัย จะทำให้เจ้ารื่นรมณ์ กับอะไรแปลกๆ เช่น การที่เจ้า ได้สูดอากาศบริสุทธิ์ หลังจากหมกอยู่ในถ้ำเหม็นๆ และชื้นแฉะมาหลายวัน$0"

}
